verysimplemodulegq2/__init__.py
verysimplemodulegq2/add.py
verysimplemodulegq2/subtract.py
verysimplemodulegq2/extras/__init__.py
verysimplemodulegq2/extras/divide.py
verysimplemodulegq2/extras/multiply.py
verysimplemodulegq2-0.0.1.dist-info/METADATA
verysimplemodulegq2-0.0.1.dist-info/WHEEL
verysimplemodulegq2-0.0.1.dist-info/top_level.txt
verysimplemodulegq2-0.0.1.dist-info/RECORD
